Workbook

Sheet All 22 Departments
A1: MEGA MNC EXCEL FORMULA GUIDE | 300+ Formulas | 22 Departments | English & Hinglish
A2: Production|Quality|Utility|Safety|Maintenance|Stores|Purchase|Finance|HR|Sales|Logistics|Planning|IT|Admin|R&D|Academy|Environmental|Costing|Customer Service|Legal|MIS|General
A3: # | B3: Excel Formula / Syntax | C3: Focus / Kaam | D3: English — What It Does | E3: Hinglish — Kaise Use Karein | F3: Hinglish — Formula Ka Naam Kya Hai | G3: MNC Real Example — Kahan Kaam Aata Hai
A4: ► 1. PRODUCTION DEPARTMENT — Utpadan Vibhag
A5: 1 | B5: =SUM(C2:C32) | C5: Monthly Output | D5: Sum of all daily production for the month. | E5: Roz ki production jodke monthly total nikalo. | F5: 'SUM'=Jod — 30 din ka total. | G5: MNC: Monthly production report — total units.
A6: 2 | B6: =D2/E2*100 | C6: Efficiency % | D6: Actual ÷ Planned × 100. | E6: Actual production target se kitni % efficient rahi. | F6: Actual/Target×100 = Efficiency %. | G6: MNC: Shift-wise daily efficiency tracking.
A7: 3 | B7: =IF(D2/E2*100>=95,"World Class",IF(D2/E2*100>=85,"Good",IF(D2/E2*100>=75,"Average","Poor"))) | C7: Efficiency Grade | D7: Auto-grades production efficiency. | E7: Efficiency % se grade auto-assign karo. | F7: IF Nested = % se grade. | G7: MNC: Daily shift grade auto-assign.
A8: 4 | B8: =(E2-F2)/E2*100 | C8: Downtime % | D8: Machine downtime percentage. | E8: Machine kitna % time band rahi. | F8: (Total-Running)/Total×100 = Downtime %. | G8: MNC: Shift report — machine downtime %.
A9: 5 | B9: =F2/E2*100 | C9: Uptime % | D9: Machine running time percentage. | E9: Machine kitna % time chali. | F9: Running/Total×100 = Uptime %. | G9: MNC: Equipment availability for OEE.
A10: 6 | B10: =(E2-F2-G2)/E2*100 | C10: OEE % | D10: Overall Equipment Effectiveness. | E10: Machine ki overall effectiveness % — 85%+ World Class. | F10: OEE=(Avail-DT-Loss)/Total×100. | G10: MNC: TPM — daily OEE tracking.
A11: 7 | B11: =D2*E2 | C11: Production Value ₹ | D11: Units produced × rate = production value. | E11: Units × rate = production ka rupay mein mool. | F11: Units × Rate = ₹ Value. | G11: MNC: Shift production value for costing.
A12: 8 | B12: =SUMIF(B:B,"Line-1",C:C) | C12: Line-wise Output | D12: Total production from Line-1. | E12: Sirf ek line ki production nikalo. | F12: 'SUMIF'=Line filter karo production jodo. | G12: MNC: Multi-line comparison report.
A13: 9 | B13: =D2-E2 | C13: Prod Variance | D13: Actual minus planned production. | E13: Actual aur plan ke beech ka farq. | F13: Actual-Plan=Variance. | G13: MNC: Daily variance — gap analysis.
A14: 10 | B14: =IF(D2>=E2,"Target Met","Short: "&(E2-D2)&" units") | C14: Target Status | D14: Met or shortfall label. | E14: Target met hua ya kitna short raha. | F14: IF=Target check — met ya shortfall. | G14: MNC: Shift manager production alert.
A15: 11 | B15: =D2*E2/60 | C15: Cycle Time min | D15: Units × time / 60 = cycle time in minutes. | E15: Ek unit banane ka cycle time minutes mein. | F15: Units×Time/60=Cycle Time. | G15: MNC: Line balancing — takt vs cycle.
A16: 12 | B16: =3600/D2 | C16: Takt Time sec | D16: Available time ÷ demand = takt time. | E16: Customer demand se takt time nikalo. | F16: 3600/Units = Takt Time seconds. | G16: MNC: Lean — takt time calculation.
A17: 13 | B17: =D2*E2 | C17: Scrap Cost ₹ | D17: Rejected units × cost per unit. | E17: Rejected units × cost = scrap loss. | F17: Rejection×Rate=Scrap Cost ₹. | G17: MNC: Monthly scrap cost — cost reduction.
A18: 14 | B18: =AVERAGE(C2:C32) | C18: Daily Avg Output | D18: Average daily production in month. | E18: Mahine mein roz ka average output. | F18: 'AVERAGE'=Avg daily production. | G18: MNC: Benchmark setting — daily target.
A19: 15 | B19: =LARGE(C2:C32,1) | C19: Best Day Output | D19: Highest single-day production. | E19: Sabse zyada production wale din ki value. | F19: 'LARGE'=Highest day output. | G19: MNC: Best shift/day benchmark.
A20: 16 | B20: =SMALL(C2:C32,1) | C20: Worst Day Output | D20: Lowest single-day production. | E20: Sabse kam production wala din. | F20: 'SMALL'=Lowest day output. | G20: MNC: Identify worst performing shift.
A21: 17 | B21: =COUNTIF(D2:D32,"Planned Shutdown") | C21: Planned Stops | D21: Count of planned shutdown days. | E21: Planned shutdown kitne din the gino. | F21: 'COUNTIF'=Planned shutdown days count. | G21: MNC: Availability factor — OEE input.
A22: 18 | B22: =COUNTIF(D2:D32,"Breakdown") | C22: Breakdown Stops | D22: Count of breakdown stoppages. | E22: Breakdown ki wajah se kitne din ruke. | F22: 'COUNTIF'=Breakdown days gino. | G22: MNC: Monthly reliability tracking.
A23: 19 | B23: =D2/E2 | C23: Yield Ratio | D23: Output units ÷ input material = yield. | E23: Input material se kitna output mila. | F23: Output/Input=Yield Ratio. | G23: MNC: Material yield tracking — waste reduction.
A24: 20 | B24: =(1-D2/E2)*100 | C24: Waste % | D24: Percentage of input wasted. | E24: Input material ka kitna % waste hua. | F24: (1-Yield)×100=Waste %. | G24: MNC: Material efficiency KPI.
A25: 21 | B25: =SUMPRODUCT((B2:B100="A Shift")*(C2:C100)) | C25: Shift-wise Total | D25: Total production of A Shift using SUMPRODUCT. | E25: A Shift ki total production — SUMPRODUCT se. | F25: SUMPRODUCT=Shift filter karke sum. | G25: MNC: Shift comparison — which shift best.
A26: 22 | B26: =D2/E2*100 | C26: Capacity Util % | D26: Actual production ÷ plant capacity × 100. | E26: Plant capacity ka kitna % use hua. | F26: Actual/Capacity×100=Utilization %. | G26: MNC: Capacity planning — over/under.
A27: 23 | B27: =IF(D2/E2*100>100,"Overloaded",IF(D2/E2*100<70,"Underutilized","Optimal")) | C27: Capacity Status | D27: Capacity status label — Optimal/Over/Under. | E27: Capacity status automatically assign karo. | F27: IF=% se status — optimal range 70-100%. | G27: MNC: Resource planning dashboard.
A28: 24 | B28: =D2*24 | C28: Hours in Days | D28: Converts days to hours for time tracking. | E28: Din ko ghante mein convert karo. | F28: Days×24=Hours. | G28: MNC: Downtime hours from days.
A29: 25 | B29: =D2/24 | C29: Days in Hours | D29: Converts hours to days. | E29: Ghante ko din mein convert karo. | F29: Hours/24=Days. | G29: MNC: Reporting — hours to days.
A30: ► 2. QUALITY DEPARTMENT (QA/QC) — Gunvatta Vibhag
A31: 26 | B31: =COUNTIF(C:C,"Rejected")/COUNTA(C:C)*100 | C31: Rejection Rate % | D31: % of parts rejected. | E31: Rejection % nikalo. | F31: Rejected/Total×100=Rejection %. | G31: MNC: Daily production rejection %.
A32: 27 | B32: =COUNTIF(C:C,"Pass")/COUNTA(C:C)*100 | C32: FPY % | D32: First Pass Yield %. | E32: Pehli baar pass % nikalo — FPY. | F32: Pass/Total×100=FPY %. | G32: MNC: Quality efficiency KPI.
A33: 28 | B33: =(COUNTIF(C:C,"Rejected")/COUNTA(C:C))*1000000 | C33: DPPM | D33: Defective Parts Per Million. | E33: DPPM = international quality KPI. | F33: (Rejected/Total)×10 lakh=DPPM. | G33: MNC: Customer quality report.
A34: 29 | B34: =IF(AND(D2>=E2,D2<=F2),"ACCEPT","REJECT") | C34: Accept/Reject | D34: Auto inspection decision. | E34: Tolerance se auto ACCEPT/REJECT. | F34: IF+AND=Tolerance check. | G34: MNC: Inspection auto-decision.
A35: 30 | B35: =D2*E2*F2 | C35: RPN FMEA | D35: Severity × Occurrence × Detection. | E35: FMEA ke liye RPN nikalo. | F35: S×O×D=RPN — risk priority. | G35: MNC: FMEA risk score.
A36: 31 | B36: =IF(D2>=100,"High",IF(D2>=50,"Medium","Low")) | C36: Risk Level | D36: FMEA risk classification. | E36: RPN se risk level assign karo. | F36: IF Nested=RPN se level. | G36: MNC: FMEA action prioritization.
A37: 32 | B37: =COUNTIFS(B:B,"Vendor-A",C:C,"Rejected") | C37: Vendor Rejection | D37: Vendor-specific rejection count. | E37: Ek vendor ke rejected parts gino. | F37: 'COUNTIFS'=Vendor+Rejected count. | G37: MNC: Vendor quality scorecard.
A38: 33 | B38: =IF(D2>=95,"A",IF(D2>=85,"B",IF(D2>=75,"C","D"))) | C38: Vendor Grade | D38: A/B/C/D vendor quality grade. | E38: Vendor score se grade assign karo. | F38: IF Nested=Score se grade. | G38: MNC: Vendor evaluation system.
A39: 34 | B39: =IF(DATEDIF(B2,TODAY(),"D")>7,"OVERDUE","Open") | C39: NCR Overdue | D39: NCR open beyond 7 days flag. | E39: 7 din se zyada khula NCR flag karo. | F39: IF+DATEDIF=7 day check. | G39: MNC: NCR closure monitoring.
A40: 35 | B40: =STDEV(D2:D100)/AVERAGE(D2:D100)*100 | C40: COV % | D40: Coefficient of Variation — process consistency. | E40: Process variation % nikalo. | F40: StdDev/Avg×100=COV %. | G40: MNC: SPC process consistency.
A41: 36 | B41: =DATEDIF(B2,C2,"D") | C41: CAPA Days | D41: Days taken to close a CAPA. | E41: CAPA close hone mein kitne din lage. | F41: 'DATEDIF'=Open to close days. | G41: MNC: CAPA closure TAT tracking.
A42: 37 | B42: =COUNTIF(D:D,"Customer Complaint") | C42: Complaints | D42: Total customer complaints. | E42: Customer complaints gino. | F42: 'COUNTIF'=Complaints count. | G42: MNC: Monthly complaint tracking.
A43: 38 | B43: =AVERAGEIF(B:B,"Incoming",D:D) | C43: Incoming Avg | D43: Average incoming inspection score. | E43: Incoming inspection average score. | F43: 'AVERAGEIF'=Incoming ka average. | G43: MNC: Vendor incoming quality avg.
A44: 39 | B44: =D2/E2*100 | C44: Inspection Eff % | D44: Parts inspected vs target. | E44: Inspection efficiency % nikalo. | F44: Actual/Target×100=Efficiency. | G44: MNC: QC inspector daily efficiency.
A45: 40 | B45: =COUNTIF(C:C,"Rework") | C45: Rework Count | D45: Total rework items in period. | E45: Kitne items rework mein gaye gino. | F45: 'COUNTIF'=Rework entries gino. | G45: MNC: Rework cost analysis.
A46: 41 | B46: =D2*E2 | C46: Rework Cost ₹ | D46: Rework units × rework cost. | E46: Rework items × cost = rework expense. | F46: Rework Units×Rate=Cost ₹. | G46: MNC: Cost of poor quality (COPQ).
A47: 42 | B47: =D2+E2+F2 | C47: COPQ Total | D47: Cost of poor quality = Scrap+Rework+Warranty. | E47: Scrap + Rework + Warranty = COPQ total. | F47: Scrap+Rework+Warranty=COPQ. | G47: MNC: Total cost of poor quality.
A48: 43 | B48: =D2/E2*100 | C48: Audit Score % | D48: Quality audit score percentage. | E48: Audit score % nikalo. | F48: Score/Total×100=Audit %. | G48: MNC: Internal/external audit score.
A49: 44 | B49: =IF(D2/E2*100>=85,"PASS","FAIL") | C49: Audit Result | D49: Audit pass/fail at 85% threshold. | E49: 85% se zyada toh PASS warna FAIL. | F49: IF=85% threshold audit result. | G49: MNC: ISO audit pass/fail decision.
A50: 45 | B50: =SUMIF(B:B,"Dimensional",D:D) | C50: Defect Type Total | D50: Sum of specific defect type. | E50: Ek defect type ka total count. | F50: 'SUMIF'=Defect type filter sum. | G50: MNC: Pareto analysis defect-wise.
A51: 46 | B51: =COUNTIFS(B:B,"Line-2",C:C,"Critical") | C51: Critical Defects | D51: Critical defects on specific line. | E51: Ek line ke critical defects gino. | F51: 'COUNTIFS'=Line+Critical count. | G51: MNC: Critical defect monitoring.
A52: 47 | B52: =D2/E2 | C52: Process Capability Cp | D52: USL-LSL divided by 6×StdDev = Cp. | E52: Process capability nikalo — Cp. | F52: (USL-LSL)/(6×Sigma)=Cp. | G52: MNC: SPC — process capability index.
A53: 48 | B53: =IF(D2>=1.33,"Capable",IF(D2>=1.0,"Marginal","Not Capable")) | C53: Cp Status | D53: Process capability status. | E53: Cp value se process status label. | F53: IF=Cp se Capable/Marginal/Not. | G53: MNC: SPC dashboard capability status.
A54: 49 | B54: =MEDIAN(D2:D100) | C54: Median Value | D54: Median of quality measurements. | E54: Data ka beech wala value nikalo. | F54: 'MEDIAN'=Middle value (not affected by outliers). | G54: MNC: Quality data central tendency.
A55: 50 | B55: =PERCENTILE(D2:D100,0.99) | C55: 99th Percentile | D55: Top 1% measurement value. | E55: Data ka 99th percentile nikalo. | F55: 'PERCENTILE'=99% data ke neeche. | G55: MNC: Extreme value analysis.
A56: ► 3. UTILITY DEPARTMENT — Upyogita Vibhag
A57: 51 | B57: =D2-C2 | C57: Consumption | D57: Closing - Opening reading. | E57: Meter reading se consumption nikalo. | F57: Closing-Opening=Consumption. | G57: MNC: Daily electricity/water consumption.
A58: 52 | B58: =(D2-C2)*E2 | C58: Utility Cost ₹ | D58: Units × rate = cost. | E58: Units × rate = rupay mein cost. | F58: Units×Rate=₹ Cost. | G58: MNC: Monthly utility bill calculate.
A59: 53 | B59: =D2/E2 | C59: SEC kWh/unit | D59: Specific Energy Consumption. | E59: Ek unit production pe energy — SEC. | F59: Energy/Production=SEC. | G59: MNC: BEE energy KPI reporting.
A60: 54 | B60: =(E2-F2-G2)/E2*100 | C60: OEE % | D60: Overall Equipment Effectiveness. | E60: Utility equipment OEE %. | F60: OEE=(Avail-DT-Loss)/Total×100. | G60: MNC: Compressor/boiler OEE.
A61: 55 | B61: =AVERAGE(D2:D32) | C61: Avg Daily | D61: Average daily consumption. | E61: Roz ka average consumption nikalo. | F61: 'AVERAGE'=Daily avg consumption. | G61: MNC: Peak vs average trend.
A62: 56 | B62: =D2*0.82 | C62: kVA to kW | D62: kVA × 0.82 = real kW power. | E62: kVA se kW convert karo — PF=0.82. | F62: kVA×PF=kW. | G62: MNC: Transformer loading.
A63: 57 | B63: =D2/E2*100 | C63: Load Factor % | D63: Actual load ÷ installed capacity × 100. | E63: Installed capacity ka % load nikalo. | F63: Actual/Capacity×100=Load %. | G63: MNC: DG/transformer overload check.
A64: 58 | B64: =AVERAGE(D2:D100) | C64: MTTR hrs | D64: Average repair time for equipment. | E64: Average breakdown repair time — MTTR. | F64: 'AVERAGE'=Mean repair time. | G64: MNC: Maintenance response time KPI.
A65: 59 | B65: =E2/COUNTIF(C:C,"Breakdown") | C65: MTBF hrs | D65: Mean Time Between Failures. | E65: Do breakdown ke beech running time. | F65: Hours/Breakdowns=MTBF. | G65: MNC: Equipment reliability score.
A66: 60 | B66: =COUNTIF(C:C,"Planned")/COUNTA(C:C)*100 | C66: PM Compliance % | D66: Preventive maintenance compliance. | E66: PM kitna % complete hua. | F66: Done/Total×100=PM %. | G66: MNC: TPM/ISO PM compliance.
A67: 61 | B67: =D2/E2*1000 | C67: Specific Water KL/T | D67: Water per ton of production. | E67: Per ton production paani ka use. | F67: Water/Production×1000=KL/Ton. | G67: MNC: Water KPI — ZLD target.
A68: 62 | B68: =D2-E2 | C68: Water Balance | D68: Inlet minus outlet = leakage. | E68: Paani ka balance — leakage detect. | F68: Inlet-Outlet=Balance/Leakage. | G68: MNC: Water audit — ZLD.
A69: 63 | B69: =(D2-E2)/E2*100 | C69: Consumption Var % | D69: Variance from target consumption. | E69: Target se actual consumption variance. | F69: (Actual-Target)/Target×100=Var %. | G69: MNC: Energy budget variance.
A70: 64 | B70: =SUM(D2:D12) | C70: Annual Units | D70: Total annual utility consumption. | E70: Saal bhar ki total consumption. | F70: 'SUM'=Annual total units. | G70: MNC: Annual energy report.
A71: 65 | B71: =D2*E2 | C71: Steam Cost ₹ | D71: Steam units × rate = steam cost. | E71: Steam units × rate = cost nikalo. | F71: Units×Rate=Steam Cost ₹. | G71: MNC: Boiler steam cost monthly.
A72: 66 | B72: =SUMIF(B:B,"Compressed Air",D:D) | C72: CA Consumption | D72: Total compressed air consumption. | E72: Compressed air ka total use nikalo. | F72: 'SUMIF'=CA type filter sum. | G72: MNC: Compressed air energy audit.
A73: 67 | B73: =D2/(D2+E2)*100 | C73: PM vs Reactive % | D73: Planned vs reactive maintenance ratio. | E73: Planned maintenance ka % ratio. | F73: Planned/(Planned+Reactive)×100. | G73: MNC: TPM proactive ratio.
A74: 68 | B74: =D2*E2*F2/1000 | C74: Solar Generation kWh | D74: Panel area × irradiation × efficiency. | E74: Solar panels se kitni energy bani. | F74: Area×Irrad×Eff/1000=kWh. | G74: MNC: Renewable energy generation.
A75: 69 | B75: =D2/E2*100 | C75: Solar % Contribution | D75: Solar energy as % of total consumption. | E75: Total consumption mein solar ka %. | F75: Solar/Total×100=Solar %. | G75: MNC: Green energy contribution KPI.
A76: 70 | B76: =IF(D2<E2,"Energy Efficient","Review Required") | C76: Energy Status | D76: Compares actual vs benchmark SEC. | E76: SEC benchmark se compare karo. | F76: IF=SEC se status label. | G76: MNC: Energy star rating check.
A77: 71 | B77: =D2*365 | C77: Annual Proj Cost | D77: Daily cost × 365 = annual projection. | E77: Roz ka cost × 365 = saal ka estimate. | F77: Daily×365=Annual Projection. | G77: MNC: Annual utility budget planning.
A78: 72 | B78: =D2/E2 | C78: Cost per KL Water | D78: Total water cost ÷ KL consumed. | E78: Per KL paani ka cost nikalo. | F78: Total Cost/KL=Per KL Cost. | G78: MNC: Water cost benchmarking.
A79: ► 4. PROTECTION / SAFETY (EHS) — Suraksha Vibhag
A80: 73 | B80: =TODAY()-B2 | C80: Safe Days | D80: Accident-free days counter. | E80: Last accident se safe din count karo. | F80: TODAY()-Date=Safe days. | G80: MNC: Safety board display.
A81: 74 | B81: =IF(TODAY()-B2>=365,"GREEN",IF(TODAY()-B2>=180,"YELLOW","RED")) | C81: Safety Color | D81: Traffic light safety status. | E81: Safe days se GREEN/YELLOW/RED. | F81: IF Nested=Days se color. | G81: MNC: Safety dashboard KPI.
A82: 75 | B82: =(COUNTIF(C:C,"LTI")*1000000)/(D2*E2) | C82: LTIFR | D82: Lost Time Injury Frequency Rate. | E82: LTIFR = global safety benchmark. | F82: (LTI×1M)/(Emp×Hours)=LTIFR. | G82: MNC: Global safety KPI reporting.
A83: 76 | B83: =(COUNTIF(C:C,"Accident")*1000000)/(D2*E2) | C83: TRIFR | D83: Total Recordable Injury Frequency Rate. | E83: TRIFR = all recordable injuries rate. | F83: (Accidents×1M)/(Emp×Hrs)=TRIFR. | G83: MNC: Total recordable incidents rate.
A84: 77 | B84: =COUNTIF(C:C,"Near Miss") | C84: Near Miss | D84: Near miss count. | E84: Near miss incidents gino. | F84: 'COUNTIF'=Near Miss count. | G84: MNC: Safety leading indicator KPI.
A85: 78 | B85: =COUNTIF(C:C,"Near Miss")/COUNTIF(C:C,"Accident") | C85: Near Miss Ratio | D85: Near miss to accident ratio. | E85: Near miss aur accident ka ratio. | F85: Near Miss/Accident=Ratio. | G85: MNC: Safety culture indicator — higher is better.
A86: 79 | B86: =COUNTIF(D:D,"Unsafe Act")+COUNTIF(D:D,"Unsafe Condition") | C86: Unsafe Obs | D86: Total unsafe observations. | E86: Unsafe acts + conditions gino. | F86: COUNTIF+COUNTIF=Total unsafe obs. | G86: MNC: Safety walk observation report.
A87: 80 | B87: =COUNTIF(E:E,"Yes")/COUNTA(E:E)*100 | C87: PPE Compliance % | D87: PPE wearing compliance %. | E87: PPE compliance % nikalo. | F87: Yes/Total×100=PPE %. | G87: MNC: Daily PPE audit tracking.
A88: 81 | B88: =D2*E2 | C88: RPN HIRA | D88: Severity × Probability = Risk score. | E88: HIRA risk score nikalo. | F88: Severity×Probability=RPN. | G88: MNC: Risk assessment — HIRA/JSA.
A89: 82 | B89: =IF(D2*E2>=15,"Unacceptable",IF(D2*E2>=8,"Tolerable","Acceptable")) | C89: Risk Decision | D89: Risk acceptability classification. | E89: RPN se risk classification karo. | F89: IF+RPN=Risk decision. | G89: MNC: Safety action required or not.
A90: 83 | B90: =COUNTIF(C:C,"Training Pending")/COUNTA(C:C)*100 | C90: Training Gap % | D90: Safety training gap %. | E90: Training pending logon ka %. | F90: Pending/Total×100=Gap %. | G90: MNC: Safety compliance gap report.
A91: 84 | B91: =IF(AVERAGE(D:D)>=90,"Excellent",IF(AVERAGE(D:D)>=75,"Good","Needs Improvement")) | C91: Audit Grade | D91: Safety audit performance grade. | E91: Average audit score se grade. | F91: IF+AVERAGE=Score se grade. | G91: MNC: Monthly safety audit grade.
A92: 85 | B92: =IF(TODAY()-B2>30,"OVERDUE","OK") | C92: Audit Overdue | D92: 30-day audit schedule check. | E92: 30 din mein audit nahi toh flag. | F92: IF+TODAY=30 day check. | G92: MNC: Safety audit compliance.
A93: 86 | B93: =D2*E2*F2 | C93: CO2 Emission | D93: Activity × Factor × Days = CO2. | E93: Carbon emission calculate karo. | F93: Qty×Factor×Days=CO2 tonnes. | G93: MNC: GHG emission tracking.
A94: 87 | B94: =COUNTIF(C:C,"Fire")+COUNTIF(C:C,"Chemical") | C94: Hazmat Incidents | D94: Fire and chemical incident count. | E94: Fire aur chemical incidents gino. | F94: COUNTIF+COUNTIF=Hazmat count. | G94: MNC: Hazardous incident tracking.
A95: 88 | B95: =D2/E2*100 | C95: Safety Score % | D95: Dept safety score vs maximum. | E95: Safety score % nikalo. | F95: Score/Max×100=Safety %. | G95: MNC: Department safety ranking.
A96: 89 | B96: =RANK(D2,D$2:D$10,0) | C96: Dept Safety Rank | D96: Ranks departments by safety score. | E96: Safety score se department rank. | F96: 'RANK'=Safety score rank. | G96: MNC: Interdepartment safety competition.
A97: 90 | B97: =COUNTIFS(B:B,"Electrical",C:C,"High") | C97: High Elec Risk | D97: High-risk electrical hazards count. | E97: Electrical + High risk count. | F97: 'COUNTIFS'=Type+Risk level count. | G97: MNC: Electrical safety audit.
A98: 91 | B98: =DATEDIF(B2,TODAY(),"D") | C98: Days Since Audit | D98: Days since last safety audit. | E98: Last audit ke baad kitne din. | F98: 'DATEDIF'=Date se aaj din. | G98: MNC: Audit frequency monitoring.
A99: 92 | B99: =D2*E2/100 | C99: Weighted Risk | D99: Risk score × weight = weighted score. | E99: Risk score weighted calculate karo. | F99: Score×Weight/100=Weighted. | G99: MNC: Multi-criteria risk ranking.
A100: ► 5. MAINTENANCE DEPARTMENT (TPM) — Anurakshan Vibhag
...

Sheet Department Index
A1: 22 DEPARTMENTS — FORMULA COUNT & KEY KPIs INDEX
A2: Dept # | B2: Department | C2: Key KPI Formulas | D2: Real MNC Application
A3: 1 | B3: PRODUCTION | C3: OEE% | Efficiency% | Downtime% | Scrap Cost | Takt Time | D3: Shift tracking, line comparison, scrap analysis
A4: 2 | B4: QUALITY | C4: DPPM | FPY% | RPN(FMEA) | ACCEPT/REJECT | Cp | D4: Inspection, vendor quality, CAPA, SPC
A5: 3 | B5: UTILITY | C5: SEC | OEE% | MTBF | Water Balance | PM% | D5: Energy audit, BEE reporting, ZLD
A6: 4 | B6: SAFETY | C6: LTIFR | TRIFR | PPE% | RPN | Safe Days | D6: Safety dashboard, HIRA, audit compliance
A7: 5 | B7: MAINTENANCE | C7: MTBF | MTTR | PM% | Availability% | Work Orders | D7: TPM, breakdown tracking, spare management
A8: 6 | B8: STORES | C8: Closing Stock | Reorder Alert | EOQ | Days of Stock | D8: Bin card, inventory valuation, ABC analysis
A9: 7 | B9: PURCHASE | C9: Saving% | Lead Time | L1/L2/L3 Rank | Payment Due | D9: Procurement KPI, vendor management
A10: 8 | B10: FINANCE | C10: GST | EMI | NPV | IRR | Growth% | Margin% | D10: P&L, budget control, investment analysis
A11: 9 | B11: HR | C11: Tenure | Net Salary | PF | ESIC | Attrition% | D11: Payroll, appraisal, headcount analytics
A12: 10 | B12: SALES | C12: Achievement% | Win Rate% | Commission | NPS | D12: Leaderboard, target tracking, territory analysis
A13: 11 | B13: LOGISTICS | C13: OTD% | Transit Days | Fill Rate% | Freight/Unit | D13: Delivery performance, freight cost analysis
... A24: 22 | B24: GENERAL | C24: IF | SUM | VLOOKUP | INDEX+MATCH | TEXT | DATE | STAT | D24: Universal formulas for all departments
